hass_deps/__init__.py
hass_deps/__main__.py
hass_deps/dependency.py
hass_deps/deps.py
hass_deps/deps_core.py
hass_deps/deps_lovelace.py
hass_deps/exceptions.py
hass_deps/source.py
hass_deps-1.0.8.dist-info/LICENSE
hass_deps-1.0.8.dist-info/METADATA
hass_deps-1.0.8.dist-info/WHEEL
hass_deps-1.0.8.dist-info/entry_points.txt
hass_deps-1.0.8.dist-info/top_level.txt
hass_deps-1.0.8.dist-info/RECORD
