Metadata-Version: 2.1
Name: hass-deps
Version: 1.0.8
Summary: 3rd party dependency manager for Home Assistant
Home-page: https://github.com/nickw444/hass-deps
Author: Nick Whyte
Author-email: nick@nickwhyte.com
License: UNKNOWN
Platform: UNKNOWN
Classifier: Programming Language :: Python
License-File: LICENSE
Requires-Dist: requests
Requires-Dist: click
Requires-Dist: ruamel-yaml
